{
  "Header": {
    "Version": 8,
    "ModelCount": 10,
    "OffsetOfModelHeaderList": 12,
    "OffsetOfModelDataList": 816
  },
  "ModelHeaderList": [
    {
      "Name": [
        65,
        108,
        0,
        0,
        0,
        0,
        0,
        0,
        0,
        0,
        0,
        0,
        0,
        0,
        0,
        0
      ],
      "RelativeOffset": 0,
      "Size": 3776,
      "OffsetToDataAboveTristrips": 32,
      "OffsetOfBoneWeights1": 116,
      "Unknown1": 176,
      "OffsetOfMeshData": 224,
      "Unknown2": 0,
      "OffsetOfBoneWeights2": 164,
      "OffsetOfNumListRef": 148,
      "OffsetOfBoneWeights3": 0,
      "Unknown3": 0,
      "Unknown4": 1,
      "Unknown5": 1,
      "Unknown6": 1,
      "CountOfBoneWeights": 1,
      "CountOfInternalMeshes": 1,
      "Unknown7": 2,
      "Unknown8": 0,
      "Unknown9": 1,
      "FillerPadding": 0
    },
    {
      "Name": [
        65,
        108,
        71,
        111,
        111,
        102,
        121,
        0,
        0,
        0,
        0,
        0,
        0,
        0,
        0,
        0
      ],
      "RelativeOffset": 3776,
      "Size": 3776,
      "OffsetToDataAboveTristrips": 32,
      "OffsetOfBoneWeights1": 116,
      "Unknown1": 176,
      "OffsetOfMeshData": 224,
      "Unknown2": 0,
      "OffsetOfBoneWeights2": 164,
      "OffsetOfNumListRef": 148,
      "OffsetOfBoneWeights3": 0,
      "Unknown3": 0,
      "Unknown4": 1,
      "Unknown5": 1,
      "Unknown6": 1,
      "CountOfBoneWeights": 1,
      "CountOfInternalMeshes": 1,
      "Unknown7": 2,
      "Unknown8": 0,
      "Unknown9": 1,
      "FillerPadding": 0
    },
    {
      "Name": [
        66,
        120,
        0,
        0,
        0,
        0,
        0,
        0,
        0,
        0,
        0,
        0,
        0,
        0,
        0,
        0
      ],
      "RelativeOffset": 7552,
      "Size": 4656,
      "OffsetToDataAboveTristrips": 32,
      "OffsetOfBoneWeights1": 116,
      "Unknown1": 176,
      "OffsetOfMeshData": 224,
      "Unknown2": 0,
      "OffsetOfBoneWeights2": 164,
      "OffsetOfNumListRef": 148,
      "OffsetOfBoneWeights3": 0,
      "Unknown3": 0,
      "Unknown4": 1,
      "Unknown5": 1,
      "Unknown6": 1,
      "CountOfBoneWeights": 1,
      "CountOfInternalMeshes": 1,
      "Unknown7": 2,
      "Unknown8": 0,
      "Unknown9": 1,
      "FillerPadding": 0
    },
    {
      "Name": [
        66,
        120,
        71,
        111,
        111,
        102,
        121,
        0,
        0,
        0,
        0,
        0,
        0,
        0,
        0,
        0
      ],
      "RelativeOffset": 12208,
      "Size": 4656,
      "OffsetToDataAboveTristrips": 32,
      "OffsetOfBoneWeights1": 116,
      "Unknown1": 176,
      "OffsetOfMeshData": 224,
      "Unknown2": 0,
      "OffsetOfBoneWeights2": 164,
      "OffsetOfNumListRef": 148,
      "OffsetOfBoneWeights3": 0,
      "Unknown3": 0,
      "Unknown4": 1,
      "Unknown5": 1,
      "Unknown6": 1,
      "CountOfBoneWeights": 1,
      "CountOfInternalMeshes": 1,
      "Unknown7": 2,
      "Unknown8": 0,
      "Unknown9": 1,
      "FillerPadding": 0
    },
    {
      "Name": [
        70,
        114,
        0,
        0,
        0,
        0,
        0,
        0,
        0,
        0,
        0,
        0,
        0,
        0,
        0,
        0
      ],
      "RelativeOffset": 16864,
      "Size": 4528,
      "OffsetToDataAboveTristrips": 32,
      "OffsetOfBoneWeights1": 116,
      "Unknown1": 176,
      "OffsetOfMeshData": 224,
      "Unknown2": 0,
      "OffsetOfBoneWeights2": 164,
      "OffsetOfNumListRef": 148,
      "OffsetOfBoneWeights3": 0,
      "Unknown3": 0,
      "Unknown4": 1,
      "Unknown5": 1,
      "Unknown6": 1,
      "CountOfBoneWeights": 1,
      "CountOfInternalMeshes": 1,
      "Unknown7": 2,
      "Unknown8": 0,
      "Unknown9": 1,
      "FillerPadding": 0
    },
    {
      "Name": [
        70,
        114,
        71,
        111,
        111,
        102,
        121,
        0,
        0,
        0,
        0,
        0,
        0,
        0,
        0,
        0
      ],
      "RelativeOffset": 21392,
      "Size": 4528,
      "OffsetToDataAboveTristrips": 32,
      "OffsetOfBoneWeights1": 116,
      "Unknown1": 176,
      "OffsetOfMeshData": 224,
      "Unknown2": 0,
      "OffsetOfBoneWeights2": 164,
      "OffsetOfNumListRef": 148,
      "OffsetOfBoneWeights3": 0,
      "Unknown3": 0,
      "Unknown4": 1,
      "Unknown5": 1,
      "Unknown6": 1,
      "CountOfBoneWeights": 1,
      "CountOfInternalMeshes": 1,
      "Unknown7": 2,
      "Unknown8": 0,
      "Unknown9": 1,
      "FillerPadding": 0
    },
    {
      "Name": [
        115,
        104,
        100,
        119,
        65,
        108,
        0,
        0,
        0,
        0,
        0,
        0,
        0,
        0,
        0,
        0
      ],
      "RelativeOffset": 25920,
      "Size": 2304,
      "OffsetToDataAboveTristrips": 32,
      "OffsetOfBoneWeights1": 116,
      "Unknown1": 176,
      "OffsetOfMeshData": 224,
      "Unknown2": 0,
      "OffsetOfBoneWeights2": 164,
      "OffsetOfNumListRef": 148,
      "OffsetOfBoneWeights3": 0,
      "Unknown3": 0,
      "Unknown4": 1,
      "Unknown5": 1,
      "Unknown6": 1,
      "CountOfBoneWeights": 1,
      "CountOfInternalMeshes": 1,
      "Unknown7": 2,
      "Unknown8": 0,
      "Unknown9": 1,
      "FillerPadding": 0
    },
    {
      "Name": [
        115,
        104,
        100,
        119,
        65,
        76,
        71,
        111,
        111,
        102,
        121,
        0,
        0,
        0,
        0,
        0
      ],
      "RelativeOffset": 28224,
      "Size": 2304,
      "OffsetToDataAboveTristrips": 32,
      "OffsetOfBoneWeights1": 116,
      "Unknown1": 176,
      "OffsetOfMeshData": 224,
      "Unknown2": 0,
      "OffsetOfBoneWeights2": 164,
      "OffsetOfNumListRef": 148,
      "OffsetOfBoneWeights3": 0,
      "Unknown3": 0,
      "Unknown4": 1,
      "Unknown5": 1,
      "Unknown6": 1,
      "CountOfBoneWeights": 1,
      "CountOfInternalMeshes": 1,
      "Unknown7": 2,
      "Unknown8": 0,
      "Unknown9": 1,
      "FillerPadding": 0
    },
    {
      "Name": [
        115,
        104,
        100,
        119,
        66,
        120,
        0,
        0,
        0,
        0,
        0,
        0,
        0,
        0,
        0,
        0
      ],
      "RelativeOffset": 30528,
      "Size": 2704,
      "OffsetToDataAboveTristrips": 32,
      "OffsetOfBoneWeights1": 116,
      "Unknown1": 176,
      "OffsetOfMeshData": 224,
      "Unknown2": 0,
      "OffsetOfBoneWeights2": 164,
      "OffsetOfNumListRef": 148,
      "OffsetOfBoneWeights3": 0,
      "Unknown3": 0,
      "Unknown4": 1,
      "Unknown5": 1,
      "Unknown6": 1,
      "CountOfBoneWeights": 1,
      "CountOfInternalMeshes": 1,
      "Unknown7": 2,
      "Unknown8": 0,
      "Unknown9": 1,
      "FillerPadding": 0
    },
    {
      "Name": [
        115,
        104,
        100,
        119,
        70,
        114,
        0,
        0,
        0,
        0,
        0,
        0,
        0,
        0,
        0,
        0
      ],
      "RelativeOffset": 33232,
      "Size": 2608,
      "OffsetToDataAboveTristrips": 32,
      "OffsetOfBoneWeights1": 116,
      "Unknown1": 176,
      "OffsetOfMeshData": 224,
      "Unknown2": 0,
      "OffsetOfBoneWeights2": 164,
      "OffsetOfNumListRef": 148,
      "OffsetOfBoneWeights3": 0,
      "Unknown3": 0,
      "Unknown4": 1,
      "Unknown5": 1,
      "Unknown6": 1,
      "CountOfBoneWeights": 1,
      "CountOfInternalMeshes": 1,
      "Unknown7": 2,
      "Unknown8": 0,
      "Unknown9": 1,
      "FillerPadding": 0
    }
  ],
  "Filler1": [
    0,
    0,
    0,
    0
  ],
  "ModelDataList": null
}
